{"id626e70121df7":{"id":"id626e70121df7","cover":"","active":"on","header":"Пузыри на коже","category":["id6263d7100f93","id6263edb61c16","id6263edc7070c","id6263f0e61415","id6263f0dc06cb"],"preset":"","blocks":"","_site":null,"_login":null,"_id":"id626e70121df7","_form":"symptoms","_table":"symptoms","_created":"2022-05-01 14:28:41","_creator":"id625eb9a80a70","_lastdate":"2022-05-01 14:28:41","_lastuser":"id625eb9a80a70","_sort":"999999999"},"id626e70ad0ca4":{"id":"id626e70ad0ca4","cover":"","active":"on","header":"Шелушение кожи","category":["id6263f0e61415"],"preset":"","blocks":"","_site":null,"_login":null,"_id":"id626e70ad0ca4","_form":"symptoms","_table":"symptoms","_created":"2022-05-01 14:29:24","_creator":"id625eb9a80a70","_lastdate":"2022-05-01 14:29:24","_lastuser":"id625eb9a80a70","_sort":"999999999"},"id626e702d0119":{"id":"id626e702d0119","cover":"","header":"Жжение кожи","category":["id6263d7100f93","id6263f0e61415"],"preset":"","blocks":"","active":"on","_site":null,"_login":null,"_id":"id626e702d0119","_form":"symptoms","_table":"symptoms","_created":"2022-05-01 14:29:57","_creator":"id625eb9a80a70","_lastdate":"2022-05-01 14:29:57","_lastuser":"id625eb9a80a70","_sort":"999999999"},"id626e710c0c60":{"id":"id626e710c0c60","cover":"","active":"on","header":"Отечные красные пятна","category":["id6263edc7070c","id6263f0e61415"],"preset":"","blocks":"","_site":null,"_login":null,"_id":"id626e710c0c60","_form":"symptoms","_table":"symptoms","_created":"2022-05-01 14:30:32","_creator":"id625eb9a80a70","_lastdate":"2022-05-01 14:30:32","_lastuser":"id625eb9a80a70","_sort":"999999999"}}